[{"code":"fr-CA","name":"fr-CA-Neural2-A","gender":"FEMALE"},{"code":"fr-CA","name":"fr-CA-Neural2-B","gender":"MALE"},{"code":"fr-CA","name":"fr-CA-Neural2-C","gender":"FEMALE"},{"code":"fr-CA","name":"fr-CA-Neural2-D","gender":"MALE"},{"code":"fr-CA","name":"fr-CA-Standard-A","gender":"FEMALE"},{"code":"fr-CA","name":"fr-CA-Standard-B","gender":"MALE"},{"code":"fr-CA","name":"fr-CA-Standard-C","gender":"FEMALE"},{"code":"fr-CA","name":"fr-CA-Standard-D","gender":"MALE"},{"code":"fr-CA","name":"fr-CA-Wavenet-A","gender":"FEMALE"},{"code":"fr-CA","name":"fr-CA-Wavenet-B","gender":"MALE"},{"code":"fr-CA","name":"fr-CA-Wavenet-C","gender":"FEMALE"},{"code":"fr-CA","name":"fr-CA-Wavenet-D","gender":"MALE"},{"code":"fr-FR","name":"fr-FR-Neural2-A","gender":"FEMALE"},{"code":"fr-FR","name":"fr-FR-Neural2-B","gender":"MALE"},{"code":"fr-FR","name":"fr-FR-Neural2-C","gender":"FEMALE"},{"code":"fr-FR","name":"fr-FR-Neural2-D","gender":"MALE"},{"code":"fr-FR","name":"fr-FR-Neural2-E","gender":"FEMALE"},{"code":"fr-FR","name":"fr-FR-Polyglot-1","gender":"MALE"},{"code":"fr-FR","name":"fr-FR-Standard-A","gender":"FEMALE"},{"code":"fr-FR","name":"fr-FR-Standard-B","gender":"MALE"},{"code":"fr-FR","name":"fr-FR-Standard-C","gender":"FEMALE"},{"code":"fr-FR","name":"fr-FR-Standard-D","gender":"MALE"},{"code":"fr-FR","name":"fr-FR-Standard-E","gender":"FEMALE"},{"code":"fr-FR","name":"fr-FR-Wavenet-A","gender":"FEMALE"},{"code":"fr-FR","name":"fr-FR-Wavenet-B","gender":"MALE"},{"code":"fr-FR","name":"fr-FR-Wavenet-C","gender":"FEMALE"},{"code":"fr-FR","name":"fr-FR-Wavenet-D","gender":"MALE"},{"code":"fr-FR","name":"fr-FR-Wavenet-E","gender":"FEMALE"}]